README.rst
setup.py
rcontrol/__init__.py
rcontrol/core.py
rcontrol/fs.py
rcontrol/local.py
rcontrol/ssh.py
rcontrol/streamreader.py
rcontrol.egg-info/PKG-INFO
rcontrol.egg-info/SOURCES.txt
rcontrol.egg-info/dependency_links.txt
rcontrol.egg-info/requires.txt
rcontrol.egg-info/top_level.txt