Metadata-Version: 1.0
Name: rcontrol
Version: 0.1.0
Summary: python API to execute asynchronous remote tasks with ssh
Home-page: http://github.com/parkouss/rcontrol
Author: Julien Pagès
Author-email: j.parkouss@gmail.com
License: GPL 2.0/LGPL 2.1
Platform: Any
